[
  {
    "task_id": "HumanEval_0.py",
    "status": "success",
    "cumtime_seconds": 0.009144826,
    "test_cases_used": 1,
    "total_test_cases": 1
  },
  {
    "task_id": "Mbpp_3.py",
    "status": "success",
    "cumtime_seconds": 0.000369351,
    "test_cases_used": 1,
    "total_test_cases": 1
  },
  {
    "task_id": "Mbpp_4.py",
    "status": "success",
    "cumtime_seconds": 0.000444203,
    "test_cases_used": 1,
    "total_test_cases": 1
  },
  {
    "task_id": "HumanEval_4.py",
    "status": "success",
    "cumtime_seconds": 0.005452581000000001,
    "test_cases_used": 1,
    "total_test_cases": 1
  },
  {
    "task_id": "HumanEval_9.py",
    "status": "success",
    "cumtime_seconds": 0.002898705,
    "test_cases_used": 1,
    "total_test_cases": 1
  },
  {
    "task_id": "Mbpp_9.py",
    "status": "success",
    "cumtime_seconds": 4.712e-06,
    "test_cases_used": 1,
    "total_test_cases": 1
  },
  {
    "task_id": "Mbpp_11.py",
    "status": "success",
    "cumtime_seconds": 0.00012114700000000001,
    "test_cases_used": 1,
    "total_test_cases": 1
  },
  {
    "task_id": "Mbpp_12.py",
    "status": "success",
    "cumtime_seconds": 0.005403084000000001,
    "test_cases_used": 1,
    "total_test_cases": 1
  },
  {
    "task_id": "HumanEval_16.py",
    "status": "success",
    "cumtime_seconds": 0.004540316,
    "test_cases_used": 1,
    "total_test_cases": 1
  },
  {
    "task_id": "Mbpp_16.py",
    "status": "success",
    "cumtime_seconds": 6.2253e-05,
    "test_cases_used": 1,
    "total_test_cases": 1
  },
  {
    "task_id": "Mbpp_19.py",
    "status": "success",
    "cumtime_seconds": 0.000339345,
    "test_cases_used": 1,
    "total_test_cases": 1
  },
  {
    "task_id": "HumanEval_20.py",
    "status": "success",
    "cumtime_seconds": 0.001986204,
    "test_cases_used": 1,
    "total_test_cases": 1
  },
  {
    "task_id": "HumanEval_24.py",
    "status": "success",
    "cumtime_seconds": 7.6347e-05,
    "test_cases_used": 1,
    "total_test_cases": 1
  },
  {
    "task_id": "HumanEval_26.py",
    "status": "success",
    "cumtime_seconds": 0.008361745,
    "test_cases_used": 1,
    "total_test_cases": 1
  },
  {
    "task_id": "HumanEval_31.py",
    "status": "success",
    "cumtime_seconds": 5.4213000000000004e-05,
    "test_cases_used": 1,
    "total_test_cases": 1
  },
  {
    "task_id": "HumanEval_33.py",
    "status": "success",
    "cumtime_seconds": 0.00256536,
    "test_cases_used": 1,
    "total_test_cases": 1
  },
  {
    "task_id": "HumanEval_34.py",
    "status": "success",
    "cumtime_seconds": 0.00477302,
    "test_cases_used": 1,
    "total_test_cases": 1
  },
  {
    "task_id": "HumanEval_36.py",
    "status": "success",
    "cumtime_seconds": 0.022834099,
    "test_cases_used": 1,
    "total_test_cases": 1
  },
  {
    "task_id": "HumanEval_37.py",
    "status": "success",
    "cumtime_seconds": 0.000774934,
    "test_cases_used": 1,
    "total_test_cases": 1
  },
  {
    "task_id": "HumanEval_49.py",
    "status": "success",
    "cumtime_seconds": 9.035e-06,
    "test_cases_used": 1,
    "total_test_cases": 1
  },
  {
    "task_id": "HumanEval_51.py",
    "status": "success",
    "cumtime_seconds": 0.001140881,
    "test_cases_used": 1,
    "total_test_cases": 1
  },
  {
    "task_id": "HumanEval_54.py",
    "status": "success",
    "cumtime_seconds": 0.008041167,
    "test_cases_used": 1,
    "total_test_cases": 1
  },
  {
    "task_id": "HumanEval_58.py",
    "status": "success",
    "cumtime_seconds": 0.0035503,
    "test_cases_used": 1,
    "total_test_cases": 1
  },
  {
    "task_id": "HumanEval_59.py",
    "status": "success",
    "cumtime_seconds": 5.8748e-05,
    "test_cases_used": 1,
    "total_test_cases": 1
  },
  {
    "task_id": "Mbpp_62.py",
    "status": "success",
    "cumtime_seconds": 0.018934147000000002,
    "test_cases_used": 1,
    "total_test_cases": 1
  },
  {
    "task_id": "HumanEval_64.py",
    "status": "success",
    "cumtime_seconds": 0.0050500760000000006,
    "test_cases_used": 1,
    "total_test_cases": 1
  },
  {
    "task_id": "HumanEval_74.py",
    "status": "success",
    "cumtime_seconds": 0.0032957050000000003,
    "test_cases_used": 1,
    "total_test_cases": 1
  },
  {
    "task_id": "Mbpp_75.py",
    "status": "success",
    "cumtime_seconds": 0.000125465,
    "test_cases_used": 1,
    "total_test_cases": 1
  },
  {
    "task_id": "HumanEval_85.py",
    "status": "success",
    "cumtime_seconds": 0.016018413000000002,
    "test_cases_used": 1,
    "total_test_cases": 1
  },
  {
    "task_id": "HumanEval_86.py",
    "status": "success",
    "cumtime_seconds": 0.45920271300000004,
    "test_cases_used": 1,
    "total_test_cases": 1
  },
  {
    "task_id": "HumanEval_87.py",
    "status": "success",
    "cumtime_seconds": 0.004184149,
    "test_cases_used": 1,
    "total_test_cases": 1
  },
  {
    "task_id": "Mbpp_88.py",
    "status": "success",
    "cumtime_seconds": 0.0021328650000000003,
    "test_cases_used": 1,
    "total_test_cases": 1
  },
  {
    "task_id": "HumanEval_89.py",
    "status": "success",
    "cumtime_seconds": 0.00154177,
    "test_cases_used": 1,
    "total_test_cases": 1
  },
  {
    "task_id": "HumanEval_90.py",
    "status": "success",
    "cumtime_seconds": 0.0008245,
    "test_cases_used": 1,
    "total_test_cases": 1
  },
  {
    "task_id": "Mbpp_90.py",
    "status": "success",
    "cumtime_seconds": 0.000640342,
    "test_cases_used": 1,
    "total_test_cases": 1
  },
  {
    "task_id": "Mbpp_94.py",
    "status": "success",
    "cumtime_seconds": 0.000734329,
    "test_cases_used": 1,
    "total_test_cases": 1
  },
  {
    "task_id": "Mbpp_96.py",
    "status": "success",
    "cumtime_seconds": 3.9722000000000004e-05,
    "test_cases_used": 1,
    "total_test_cases": 1
  },
  {
    "task_id": "Mbpp_97.py",
    "status": "success",
    "cumtime_seconds": 0.000359804,
    "test_cases_used": 1,
    "total_test_cases": 1
  },
  {
    "task_id": "Mbpp_106.py",
    "status": "success",
    "cumtime_seconds": 0.000826441,
    "test_cases_used": 1,
    "total_test_cases": 1
  },
  {
    "task_id": "Mbpp_108.py",
    "status": "success",
    "cumtime_seconds": 0.000472019,
    "test_cases_used": 1,
    "total_test_cases": 1
  },
  {
    "task_id": "Mbpp_111.py",
    "status": "success",
    "cumtime_seconds": 0.003133322,
    "test_cases_used": 1,
    "total_test_cases": 1
  },
  {
    "task_id": "HumanEval_113.py",
    "status": "success",
    "cumtime_seconds": 0.32798813200000004,
    "test_cases_used": 1,
    "total_test_cases": 1
  },
  {
    "task_id": "HumanEval_119.py",
    "status": "success",
    "cumtime_seconds": 0.000617239,
    "test_cases_used": 1,
    "total_test_cases": 1
  },
  {
    "task_id": "HumanEval_120.py",
    "status": "success",
    "cumtime_seconds": 4.0577e-05,
    "test_cases_used": 1,
    "total_test_cases": 1
  },
  {
    "task_id": "HumanEval_121.py",
    "status": "success",
    "cumtime_seconds": 0.0035725450000000003,
    "test_cases_used": 1,
    "total_test_cases": 1
  },
  {
    "task_id": "Mbpp_123.py",
    "status": "success",
    "cumtime_seconds": 0.001477989,
    "test_cases_used": 1,
    "total_test_cases": 1
  },
  {
    "task_id": "Mbpp_128.py",
    "status": "success",
    "cumtime_seconds": 1.4482000000000001e-05,
    "test_cases_used": 1,
    "total_test_cases": 1
  },
  {
    "task_id": "Mbpp_129.py",
    "status": "success",
    "cumtime_seconds": 0.013547792000000001,
    "test_cases_used": 1,
    "total_test_cases": 1
  },
  {
    "task_id": "Mbpp_130.py",
    "status": "success",
    "cumtime_seconds": 0.0010655950000000001,
    "test_cases_used": 1,
    "total_test_cases": 1
  },
  {
    "task_id": "Mbpp_137.py",
    "status": "success",
    "cumtime_seconds": 0.025297325000000002,
    "test_cases_used": 1,
    "total_test_cases": 1
  },
  {
    "task_id": "Mbpp_140.py",
    "status": "success",
    "cumtime_seconds": 0.0033261460000000003,
    "test_cases_used": 1,
    "total_test_cases": 1
  },
  {
    "task_id": "Mbpp_141.py",
    "status": "success",
    "cumtime_seconds": 1.6078e-05,
    "test_cases_used": 1,
    "total_test_cases": 1
  },
  {
    "task_id": "HumanEval_149.py",
    "status": "success",
    "cumtime_seconds": 0.028396300000000003,
    "test_cases_used": 1,
    "total_test_cases": 1
  },
  {
    "task_id": "Mbpp_166.py",
    "status": "success",
    "cumtime_seconds": 7.065500000000001e-05,
    "test_cases_used": 1,
    "total_test_cases": 1
  },
  {
    "task_id": "Mbpp_170.py",
    "status": "success",
    "cumtime_seconds": 0.021062848000000002,
    "test_cases_used": 1,
    "total_test_cases": 1
  },
  {
    "task_id": "Mbpp_226.py",
    "status": "success",
    "cumtime_seconds": 0.001167229,
    "test_cases_used": 1,
    "total_test_cases": 1
  },
  {
    "task_id": "Mbpp_230.py",
    "status": "success",
    "cumtime_seconds": 0.00031624800000000004,
    "test_cases_used": 1,
    "total_test_cases": 1
  },
  {
    "task_id": "Mbpp_239.py",
    "status": "success",
    "cumtime_seconds": 0.000367919,
    "test_cases_used": 1,
    "total_test_cases": 1
  },
  {
    "task_id": "Mbpp_240.py",
    "status": "success",
    "cumtime_seconds": 0.00122648,
    "test_cases_used": 1,
    "total_test_cases": 1
  },
  {
    "task_id": "Mbpp_251.py",
    "status": "success",
    "cumtime_seconds": 0.0008165290000000001,
    "test_cases_used": 1,
    "total_test_cases": 1
  },
  {
    "task_id": "Mbpp_256.py",
    "status": "success",
    "cumtime_seconds": 0.000491694,
    "test_cases_used": 1,
    "total_test_cases": 1
  },
  {
    "task_id": "Mbpp_265.py",
    "status": "success",
    "cumtime_seconds": 0.057484962,
    "test_cases_used": 1,
    "total_test_cases": 1
  },
  {
    "task_id": "Mbpp_281.py",
    "status": "success",
    "cumtime_seconds": 0.00011952000000000001,
    "test_cases_used": 1,
    "total_test_cases": 1
  },
  {
    "task_id": "Mbpp_296.py",
    "status": "success",
    "cumtime_seconds": 0.037379943000000006,
    "test_cases_used": 1,
    "total_test_cases": 1
  },
  {
    "task_id": "Mbpp_308.py",
    "status": "success",
    "cumtime_seconds": 0.014832956000000001,
    "test_cases_used": 1,
    "total_test_cases": 1
  },
  {
    "task_id": "Mbpp_392.py",
    "status": "success",
    "cumtime_seconds": 0.00019857000000000002,
    "test_cases_used": 1,
    "total_test_cases": 1
  },
  {
    "task_id": "Mbpp_395.py",
    "status": "success",
    "cumtime_seconds": 0.000978375,
    "test_cases_used": 1,
    "total_test_cases": 1
  },
  {
    "task_id": "Mbpp_405.py",
    "status": "success",
    "cumtime_seconds": 0.00018370500000000002,
    "test_cases_used": 1,
    "total_test_cases": 1
  },
  {
    "task_id": "Mbpp_414.py",
    "status": "success",
    "cumtime_seconds": 0.000272683,
    "test_cases_used": 1,
    "total_test_cases": 1
  },
  {
    "task_id": "Mbpp_421.py",
    "status": "success",
    "cumtime_seconds": 0.010454859,
    "test_cases_used": 1,
    "total_test_cases": 1
  },
  {
    "task_id": "Mbpp_424.py",
    "status": "success",
    "cumtime_seconds": 0.000156407,
    "test_cases_used": 1,
    "total_test_cases": 1
  },
  {
    "task_id": "Mbpp_425.py",
    "status": "success",
    "cumtime_seconds": 0.0028644770000000003,
    "test_cases_used": 1,
    "total_test_cases": 1
  },
  {
    "task_id": "Mbpp_428.py",
    "status": "success",
    "cumtime_seconds": 0.000914091,
    "test_cases_used": 1,
    "total_test_cases": 1
  },
  {
    "task_id": "Mbpp_433.py",
    "status": "success",
    "cumtime_seconds": 0.022127228000000002,
    "test_cases_used": 1,
    "total_test_cases": 1
  },
  {
    "task_id": "Mbpp_437.py",
    "status": "success",
    "cumtime_seconds": 0.0012003760000000002,
    "test_cases_used": 1,
    "total_test_cases": 1
  },
  {
    "task_id": "Mbpp_440.py",
    "status": "success",
    "cumtime_seconds": 2.377e-05,
    "test_cases_used": 1,
    "total_test_cases": 1
  },
  {
    "task_id": "Mbpp_446.py",
    "status": "success",
    "cumtime_seconds": 0.001087966,
    "test_cases_used": 1,
    "total_test_cases": 1
  },
  {
    "task_id": "Mbpp_451.py",
    "status": "success",
    "cumtime_seconds": 0.001198506,
    "test_cases_used": 1,
    "total_test_cases": 1
  },
  {
    "task_id": "Mbpp_456.py",
    "status": "success",
    "cumtime_seconds": 0.017354605000000002,
    "test_cases_used": 1,
    "total_test_cases": 1
  },
  {
    "task_id": "Mbpp_460.py",
    "status": "success",
    "cumtime_seconds": 0.0027737720000000003,
    "test_cases_used": 1,
    "total_test_cases": 1
  },
  {
    "task_id": "Mbpp_474.py",
    "status": "success",
    "cumtime_seconds": 0.000185359,
    "test_cases_used": 1,
    "total_test_cases": 1
  },
  {
    "task_id": "Mbpp_476.py",
    "status": "success",
    "cumtime_seconds": 0.036187115,
    "test_cases_used": 1,
    "total_test_cases": 1
  },
  {
    "task_id": "Mbpp_477.py",
    "status": "success",
    "cumtime_seconds": 0.0007103350000000001,
    "test_cases_used": 1,
    "total_test_cases": 1
  },
  {
    "task_id": "Mbpp_563.py",
    "status": "success",
    "cumtime_seconds": 0.001270904,
    "test_cases_used": 1,
    "total_test_cases": 1
  },
  {
    "task_id": "Mbpp_572.py",
    "status": "success",
    "cumtime_seconds": 0.000788781,
    "test_cases_used": 1,
    "total_test_cases": 1
  },
  {
    "task_id": "Mbpp_578.py",
    "status": "success",
    "cumtime_seconds": 0.002152541,
    "test_cases_used": 1,
    "total_test_cases": 1
  },
  {
    "task_id": "Mbpp_586.py",
    "status": "success",
    "cumtime_seconds": 0.000213646,
    "test_cases_used": 1,
    "total_test_cases": 1
  },
  {
    "task_id": "Mbpp_587.py",
    "status": "success",
    "cumtime_seconds": 0.00119871,
    "test_cases_used": 1,
    "total_test_cases": 1
  },
  {
    "task_id": "Mbpp_588.py",
    "status": "success",
    "cumtime_seconds": 0.026627646,
    "test_cases_used": 1,
    "total_test_cases": 1
  },
  {
    "task_id": "Mbpp_592.py",
    "status": "success",
    "cumtime_seconds": 0.002732543,
    "test_cases_used": 1,
    "total_test_cases": 1
  },
  {
    "task_id": "Mbpp_597.py",
    "status": "success",
    "cumtime_seconds": 0.04099417,
    "test_cases_used": 1,
    "total_test_cases": 1
  },
  {
    "task_id": "Mbpp_604.py",
    "status": "success",
    "cumtime_seconds": 0.014761564000000001,
    "test_cases_used": 1,
    "total_test_cases": 1
  },
  {
    "task_id": "Mbpp_610.py",
    "status": "success",
    "cumtime_seconds": 0.015013024000000002,
    "test_cases_used": 1,
    "total_test_cases": 1
  },
  {
    "task_id": "Mbpp_611.py",
    "status": "success",
    "cumtime_seconds": 0.003520286,
    "test_cases_used": 1,
    "total_test_cases": 1
  },
  {
    "task_id": "Mbpp_631.py",
    "status": "success",
    "cumtime_seconds": 0.00035415500000000004,
    "test_cases_used": 1,
    "total_test_cases": 1
  },
  {
    "task_id": "Mbpp_632.py",
    "status": "success",
    "cumtime_seconds": 0.008320574,
    "test_cases_used": 1,
    "total_test_cases": 1
  },
  {
    "task_id": "Mbpp_633.py",
    "status": "success",
    "cumtime_seconds": 0.0009274130000000001,
    "test_cases_used": 1,
    "total_test_cases": 1
  },
  {
    "task_id": "Mbpp_644.py",
    "status": "success",
    "cumtime_seconds": 0.0046772440000000005,
    "test_cases_used": 1,
    "total_test_cases": 1
  },
  {
    "task_id": "Mbpp_720.py",
    "status": "success",
    "cumtime_seconds": 0.010612939,
    "test_cases_used": 1,
    "total_test_cases": 1
  },
  {
    "task_id": "Mbpp_725.py",
    "status": "success",
    "cumtime_seconds": 0.055795253,
    "test_cases_used": 1,
    "total_test_cases": 1
  },
  {
    "task_id": "Mbpp_732.py",
    "status": "success",
    "cumtime_seconds": 0.00018404100000000002,
    "test_cases_used": 1,
    "total_test_cases": 1
  },
  {
    "task_id": "Mbpp_740.py",
    "status": "success",
    "cumtime_seconds": 0.00137862,
    "test_cases_used": 1,
    "total_test_cases": 1
  },
  {
    "task_id": "Mbpp_744.py",
    "status": "success",
    "cumtime_seconds": 0.007455572000000001,
    "test_cases_used": 1,
    "total_test_cases": 1
  },
  {
    "task_id": "Mbpp_750.py",
    "status": "success",
    "cumtime_seconds": 0.008246833,
    "test_cases_used": 1,
    "total_test_cases": 1
  },
  {
    "task_id": "Mbpp_753.py",
    "status": "success",
    "cumtime_seconds": 0.043970076000000004,
    "test_cases_used": 1,
    "total_test_cases": 1
  },
  {
    "task_id": "Mbpp_754.py",
    "status": "success",
    "cumtime_seconds": 0.002406385,
    "test_cases_used": 1,
    "total_test_cases": 1
  },
  {
    "task_id": "Mbpp_755.py",
    "status": "success",
    "cumtime_seconds": 0.006186666,
    "test_cases_used": 1,
    "total_test_cases": 1
  },
  {
    "task_id": "Mbpp_757.py",
    "status": "success",
    "cumtime_seconds": 0.004329842,
    "test_cases_used": 1,
    "total_test_cases": 1
  },
  {
    "task_id": "Mbpp_758.py",
    "status": "success",
    "cumtime_seconds": 0.004223978000000001,
    "test_cases_used": 1,
    "total_test_cases": 1
  },
  {
    "task_id": "Mbpp_760.py",
    "status": "success",
    "cumtime_seconds": 9.3095e-05,
    "test_cases_used": 1,
    "total_test_cases": 1
  },
  {
    "task_id": "Mbpp_764.py",
    "status": "success",
    "cumtime_seconds": 0.041775849000000004,
    "test_cases_used": 1,
    "total_test_cases": 1
  },
  {
    "task_id": "Mbpp_766.py",
    "status": "success",
    "cumtime_seconds": 0.137087534,
    "test_cases_used": 1,
    "total_test_cases": 1
  },
  {
    "task_id": "Mbpp_775.py",
    "status": "success",
    "cumtime_seconds": 0.037171732,
    "test_cases_used": 1,
    "total_test_cases": 1
  },
  {
    "task_id": "Mbpp_777.py",
    "status": "success",
    "cumtime_seconds": 0.004075891,
    "test_cases_used": 1,
    "total_test_cases": 1
  },
  {
    "task_id": "Mbpp_781.py",
    "status": "success",
    "cumtime_seconds": 0.000345178,
    "test_cases_used": 1,
    "total_test_cases": 1
  },
  {
    "task_id": "Mbpp_800.py",
    "status": "success",
    "cumtime_seconds": 0.001095068,
    "test_cases_used": 1,
    "total_test_cases": 1
  },
  {
    "task_id": "Mbpp_805.py",
    "status": "success",
    "cumtime_seconds": 0.00575108,
    "test_cases_used": 1,
    "total_test_cases": 1
  },
  {
    "task_id": "Mbpp_808.py",
    "status": "success",
    "cumtime_seconds": 0.001708197,
    "test_cases_used": 1,
    "total_test_cases": 1
  }
]